README.md
mapBrain.py
setup.cfg
setup.py
mapBrain.egg-info/PKG-INFO
mapBrain.egg-info/SOURCES.txt
mapBrain.egg-info/dependency_links.txt
mapBrain.egg-info/requires.txt
mapBrain.egg-info/top_level.txt