Metadata-Version: 1.1
Name: mapBrain
Version: 0.9.3
Summary: Brain image feature extraction and visualization
Home-page: https://github.com/SiPBA/mapBrain
Author: SIPBA@UGR
Author-email: sipba@ugr.es
License: GPL-3.0+
Download-URL: https://github.com/SiPBA/mapBrain/archive/0.9.1.tar.gz
Keywords: brain,image,analysis,feature,neuroimaging,texture,mapping,visualization
Platform: UNKNOWN
Classifier: Development Status :: 4 - Beta
Classifier: Environment :: Console
Classifier: Intended Audience :: Science/Research
Classifier: Topic :: Scientific/Engineering
Classifier: Operating System :: OS Independent
Classifier: License :: OSI Approved :: GNU General Public License v3 (GPLv3)
Classifier: Programming Language :: Python :: 3
Classifier: Programming Language :: Python :: 3.5
Classifier: Programming Language :: Python :: 3.6
